CMakeLists.txt
MANIFEST.in
README.md
requirements.txt
setup.py
cattledb/__init__.py
cattledb/wsgi.py
cattledb.egg-info/PKG-INFO
cattledb.egg-info/SOURCES.txt
cattledb.egg-info/dependency_links.txt
cattledb.egg-info/entry_points.txt
cattledb.egg-info/not-zip-safe
cattledb.egg-info/requires.txt
cattledb.egg-info/top_level.txt
cattledb/commands/__init__.py
cattledb/commands/base.py
cattledb/core/__init__.py
cattledb/core/_timeseries.py
cattledb/core/helper.py
cattledb/core/models.py
cattledb/directclient/__init__.py
cattledb/grpcclient/__init__.py
cattledb/grpcserver/__init__.py
cattledb/grpcserver/cdb_pb2.py
cattledb/grpcserver/cdb_pb2_grpc.py
cattledb/grpcserver/services.py
cattledb/restserver/__init__.py
cattledb/restserver/ext.py
cattledb/restserver/s_services.py
cattledb/restserver/services.py
cattledb/settings/__init__.py
cattledb/settings/default.py
cattledb/settings/testing.py
cattledb/storage/__init__.py
cattledb/storage/connection.py
cattledb/storage/models.py
cattledb/storage/stores.py
cattledb/storage/engines/__init__.py
cattledb/storage/engines/base.py
cattledb/storage/engines/bigtable.py
cattledb/storage/engines/localsql.py
pybind11/.appveyor.yml
pybind11/.git
pybind11/.gitignore
pybind11/.gitmodules
pybind11/.readthedocs.yml
pybind11/.travis.yml
pybind11/CMakeLists.txt
pybind11/CONTRIBUTING.md
pybind11/ISSUE_TEMPLATE.md
pybind11/LICENSE
pybind11/MANIFEST.in
pybind11/README.md
pybind11/setup.cfg
pybind11/setup.py
pybind11/docs/Doxyfile
pybind11/docs/Makefile
pybind11/docs/basics.rst
pybind11/docs/benchmark.py
pybind11/docs/benchmark.rst
pybind11/docs/changelog.rst
pybind11/docs/classes.rst
pybind11/docs/compiling.rst
pybind11/docs/conf.py
pybind11/docs/faq.rst
pybind11/docs/index.rst
pybind11/docs/intro.rst
pybind11/docs/limitations.rst
pybind11/docs/pybind11-logo.png
pybind11/docs/pybind11_vs_boost_python1.png
pybind11/docs/pybind11_vs_boost_python1.svg
pybind11/docs/pybind11_vs_boost_python2.png
pybind11/docs/pybind11_vs_boost_python2.svg
pybind11/docs/reference.rst
pybind11/docs/release.rst
pybind11/docs/requirements.txt
pybind11/docs/upgrade.rst
pybind11/docs/_static/theme_overrides.css
pybind11/docs/advanced/classes.rst
pybind11/docs/advanced/embedding.rst
