Metadata-Version: 2.1
Name: cattledb
Version: 0.6.0
Summary: Device Data Store on BigTable
Home-page: https://github.com/wuttem
Author: Matthias Wutte
Author-email: matthias.wutte@gmail.com
License: UNKNOWN
Keywords: cattledb
Platform: UNKNOWN
Provides-Extra: rest
